{
  "question_id": "1903aded",
  "question": "I think we discussed work from home jobs for seniors earlier. Can you remind me what was the 7th job in the list you provided?",
  "question_type": "single-session-assistant",
  "retrieved_sessions": [
    "da36bc2c_2",
    "66369fde_1",
    "9b4c070c",
    "sharegpt_64onasJ_0",
    "fa68c9d6_1"
  ],
  "retrieved_scores": [
    26.944579068093322,
    26.16750533304882,
    25.147538329867466,
    24.9014501617715,
    23.00569334724896
  ],
  "method": "bm25",
  "k": 5
}