{
  "question_id": "2bf43736",
  "question": "I was going through our previous chat and I wanted to clarify something about the prayer of beginners in Tanqueray's Spiritual Life treatise. Can you remind me which chapter of the second part discusses vocal prayer and meditation?",
  "question_type": "single-session-assistant",
  "retrieved_sessions": [
    "answer_sharegpt_2kpncbX_13",
    "8897a2e5",
    "16c3be68_1",
    "2e89bd03_1",
    "01d5c897_1"
  ],
  "retrieved_scores": [
    92.39470732293898,
    51.85056427319623,
    43.02585536757083,
    33.45141409581263,
    31.251426247206343
  ],
  "method": "bm25",
  "k": 5
}